{"version":2,"generated_at":"2026-06-23T06:38:35+00:00","expires_at":"2026-06-23T06:48:35+00:00","profiles":[{"quota":{"quota_status":"ok"},"rules":[],"adblock":{"enabled":false},"devices":[{"name":"Local Test","device_id":"local-device","source_ip":"127.0.0.1"}],"privacy":{"enabled":false},"user_id":"1","version":1,"parental":{"enabled":false},"security":{"enabled":false},"profile_id":"b669c1","block_response":"nxdomain","default_action":"allow"}],"rulesets":[],"upstreams":[{"address":"1.1.1.1:53","protocol":"udp","timeout":"1500ms"}],"runtime":{"dnssec_validate":false,"ecs_enabled":false,"qname_minimization":false},"signature":null,"checksum":"sha256:539858cc3fb0dbd236d873a3969fe29ca670aa2b9df7f095b927eb2d19cfd690"}